16BIT/fp_norm.v
`timescale 1ns / 1ps

module fadd_norm (rm,is_nan,is_inf,inf_nan_frac,sign,temp_exp,cal_frac,s);
	input [14:0] cal_frac;
	input [9:0] inf_nan_frac;
	input [4:0] temp_exp;
	input [1:0] rm;
	input is_nan,is_inf;
	input sign;
	output [15:0] s;
	wire [15:0] f3,f2,f1,f0;
	//從左邊找到第一個1
	wire [3:0] zeros;

	assign zeros[3] = ~|cal_frac[13:6]; // 8-bit 0
	assign f3 = zeros[3]?  {cal_frac[5:0],8'b0} : cal_frac[13:0];
	assign zeros[2] = ~|f3[13:10]; // 4-bit 0
	assign f2 = zeros[2]? {f3[9:0], 4'b0} : f3;
	assign zeros[1] = ~|f2[13:12]; // 2-bit 0
	assign f1 = zeros[1]? {f2[11:0], 2'b0} : f2;
	assign zeros[0] = ~f1[13]; // 1-bit 0
	assign f0 = zeros[0]? {f1[12:0], 1'b0} : f1;
	reg [13:0] frac0;
	reg [4:0] exp0;
	//位移以及修改exponent
	always @ * begin
		if (cal_frac[14]) begin
			frac0 = cal_frac[14:1]; // 1x.xxxxxxxxxxxxxxxxxxxxxxx xxx
			exp0 = temp_exp + 8'h1; // 1.xxxxxxxxxxxxxxxxxxxxxxx xxx
		end 
		else begin
			if ((temp_exp > zeros) && (f0[13])) begin // a normalized number
				exp0 = temp_exp - zeros;
				frac0 = f0; // 01.xxxxxxxxxxxxxxxxxxxxxxx xxx
			end
			else begin // is a denormalized number or 0
				exp0 = 0;
				if (temp_exp != 0) // (e - 127) = ((e - 1) - 126)
					frac0 = cal_frac[13:0] << (temp_exp - 8'h1);
				else frac0 = cal_frac[13:0];
			end
		end
	end
	//依照選取的模式執行round
	wire frac_plus_1 = // for rounding
	~rm[1] & ~rm[0] & frac0[2] & (frac0[1] | frac0[0]) |
	~rm[1] & ~rm[0] & frac0[2] & ~frac0[1] & ~frac0[0] & frac0[3] |
	~rm[1] & rm[0] & (frac0[2] | frac0[1] | frac0[0]) & sign |
	rm[1] & ~rm[0] & (frac0[2] | frac0[1] | frac0[0]) & ~sign;
	wire [11:0] frac_round = {1'b0,frac0[13:3]} + frac_plus_1;
	wire [4:0] exponent = frac_round[11]? exp0 + 5'h1 : exp0;
	wire overflow = &exp0 | &exponent;
	assign s = final_result(overflow, rm, sign, is_nan, is_inf, exponent, frac_round[9:0], inf_nan_frac);
	//處理例外狀況
	function [15:0] final_result;
		input overflow;
		input [1:0] rm;
		input sign, is_nan, is_inf;
		input [4:0] exponent;
		input [9:0] fraction, inf_nan_frac;
		casex ({overflow, rm, sign, is_nan, is_inf})
			6'b1_00_x_0_x : final_result = {sign,5'h1f,10'h0}; // inf
			6'b1_01_0_0_x : final_result = {sign,5'h1e,10'h3ff}; // max
			6'b1_01_1_0_x : final_result = {sign,5'h1f,10'h000}; // inf
			6'b1_10_0_0_x : final_result = {sign,5'h1f,10'h000}; // inf
			6'b1_10_1_0_x : final_result = {sign,5'h1e,10'h3ff}; // max
			6'b1_11_x_0_x : final_result = {sign,5'h1e,10'h3ff}; // max
			6'b0_xx_x_0_0 : final_result = {sign,exponent,fraction}; // nor
			6'bx_xx_x_1_x : final_result = {1'b1,5'h1f,inf_nan_frac}; // nan
			6'bx_xx_x_0_1 : final_result = {sign,5'h1f,inf_nan_frac}; // inf
			default : final_result = {sign,5'h00,10'h000}; // 0
		endcase
	endfunction
endmodule

16BIT/fp_reg_cal_norm.v
`timescale 1ns / 1ps
//////////////////////////////////////////////////////////////////////////////////
// Company: 
// Engineer: 
// 
// Create Date:    11:26:12 03/24/2017 
// Design Name: 
// Module Name:    float_adder 
// Project Name: 
// Target Devices: 
// Tool versions: 
// Description: 
//
// Dependencies: 
//
// Revision: 
// Revision 0.01 - File Created
// Additional Comments: 
//
//////////////////////////////////////////////////////////////////////////////////
module reg_cal_norm (c_rm,c_is_nan,c_is_inf,c_inf_nan_frac,c_sign,c_exp,
c_frac,clk,clrn,e,n_rm,n_is_nan,n_is_inf,
n_inf_nan_frac,n_sign,n_exp,n_frac); // pipeline regs
	input [14:0] c_frac;
	input [9:0] c_inf_nan_frac;
	input [4:0] c_exp;
	input [1:0] c_rm;
	input c_is_nan, c_is_inf, c_sign;
	input e; // e: enable
	input clk, clrn; // clock and reset
	output reg [14:0] n_frac;
	output reg [9:0] n_inf_nan_frac;
	output reg [4:0] n_exp;
	output reg [1:0] n_rm;
	output reg n_is_nan,n_is_inf,n_sign;
	always @ (posedge clk or negedge clrn) begin
		if (!clrn) begin
			n_rm <= 0;
			n_is_nan <= 0;
			n_is_inf <= 0;
			n_inf_nan_frac <= 0;
			n_sign <= 0;
			n_exp <= 0;
			n_frac <= 0;
		end else if (e) begin
			n_rm <= c_rm;
			n_is_nan <= c_is_nan;
			n_is_inf <= c_is_inf;
			n_inf_nan_frac <= c_inf_nan_frac;
			n_sign <= c_sign;
			n_exp <= c_exp;
			n_frac <= c_frac;
		end
	end
endmodule

16BIT/fp_cal.v
`timescale 1ns / 1ps

module fadd_cal (op_sub,large_frac11,small_frac14, cal_frac); // calculation
	input [10:0] large_frac11;
	input op_sub;
	input [13:0] small_frac14;
	output [14:0] cal_frac;
	//補上grs,以及避免溢位狀況,共28bit
	wire [13:0] aligned_large_frac = {1'b0,large_frac11,3'b000};
	wire [13:0] aligned_small_frac = {1'b0,small_frac14};
	//相減或相加
	assign cal_frac = op_sub?
	aligned_large_frac - aligned_small_frac :
	aligned_large_frac + aligned_small_frac;
endmodule

16BIT/fp_reg_align_cal.v
`timescale 1ns / 1ps
//////////////////////////////////////////////////////////////////////////////////
// Company: 
// Engineer: 
// 
// Create Date:    12:16:19 04/07/2017 
// Design Name: 
// Module Name:    float_control_2 
// Project Name: 
// Target Devices: 
// Tool versions: 
// Description: 
//
// Dependencies: 
//
// Revision: 
// Revision 0.01 - File Created
// Additional Comments: 
//
//////////////////////////////////////////////////////////////////////////////////
module reg_align_cal (a_rm,a_is_nan,a_is_inf,a_inf_nan_frac,a_sign,a_exp,
a_op_sub,a_large_frac,a_small_frac,clk,clrn,e,c_rm,
c_is_nan,c_is_inf,c_inf_nan_frac,c_sign,c_exp,
c_op_sub,c_large_frac,c_small_frac); // pipeline regs
	input [13:0] a_small_frac;
	input [10:0] a_large_frac;
	input [9:0] a_inf_nan_frac;
	input [4:0] a_exp;
	input [1:0] a_rm;
	input a_is_nan, a_is_inf, a_sign, a_op_sub;
	input e; // e: enable
	input clk, clrn; // clock and reset
	output reg [13:0] c_small_frac;
	output reg [10:0] c_large_frac;
	output reg [9:0] c_inf_nan_frac;
	output reg [4:0] c_exp;
	output reg [1:0] c_rm;
	output reg c_is_nan,c_is_inf,c_sign,c_op_sub;
	always @ (posedge clk or negedge clrn) begin
		if (!clrn) begin
			c_rm <= 0;
			c_is_nan <= 0;
			c_is_inf <= 0;
			c_inf_nan_frac <= 0;
			c_sign <= 0;
			c_exp <= 0;
			c_op_sub <= 0;
			c_large_frac <= 0;
			c_small_frac <= 0;
		end else if (e) begin
			c_rm <= a_rm;
			c_is_nan <= a_is_nan;
			c_is_inf <= a_is_inf;
			c_inf_nan_frac <= a_inf_nan_frac;
			c_sign <= a_sign;
			c_exp <= a_exp;
			c_op_sub <= a_op_sub;
			c_large_frac <= a_large_frac;
			c_small_frac <= a_small_frac;
		end
	end
endmodule

16BIT/fp_align.v
`timescale 1ns / 1ps

module fadd_align (a,b,sub,s_is_nan,s_is_inf,inf_nan_frac,sign,temp_exp,op_sub,large_frac11,small_frac14); //alignment stage
	input [15:0] a,b;
	input sub;
	output [13:0] small_frac14;
	output [10:0] large_frac11;
	output [9:0] inf_nan_frac;
	output [4:0] temp_exp;
	output s_is_nan;
	output s_is_inf;
	output sign;
	output op_sub;
	//不看sign bit,判斷a or b大
	wire exchange = (b[14:0] > a[14:0]);
	wire [15:0] fp_large = exchange? b : a;
	wire [15:0] fp_small = exchange? a : b;
	//轉成1.f格式
	wire fp_large_hidden_bit = |fp_large[14:10];
	wire fp_small_hidden_bit = |fp_small[14:10];
	wire [10:0] large_frac11 = {fp_large_hidden_bit,fp_large[9:0]};
	wire [10:0] small_frac11 = {fp_small_hidden_bit,fp_small[9:0]};
	//儲存較大數的exponent
	assign temp_exp = fp_large[14:10];
	//判斷正負
	assign sign = exchange? sub^b[15] : a[15];
	//使用sub or add
	assign op_sub = sub ^ fp_large[15] ^ fp_small[15];
	//例外狀況
	wire fp_large_expo_is_ff = &fp_large[14:10]; // exp == 0xff
	wire fp_small_expo_is_ff = &fp_small[14:10];
	wire fp_large_frac_is_00 = ~|fp_large[9:0]; // frac == 0x0
	wire fp_small_frac_is_00 = ~|fp_small[9:0];
	wire fp_large_is_inf=fp_large_expo_is_ff & fp_large_frac_is_00;
	wire fp_small_is_inf=fp_small_expo_is_ff & fp_small_frac_is_00;
	wire fp_large_is_nan=fp_large_expo_is_ff & ~fp_large_frac_is_00;
	wire fp_small_is_nan=fp_small_expo_is_ff & ~fp_small_frac_is_00;
	assign s_is_inf = fp_large_is_inf | fp_small_is_inf;
	wire s_is_nan = fp_large_is_nan | fp_small_is_nan | ((sub ^ fp_small[15] ^ fp_large[15]) & fp_large_is_inf & fp_small_is_inf);
	wire [9:0] nan_frac = (a[8:0] > b[8:0])?	{1'b1,a[8:0]} : {1'b1,b[8:0]};
	assign inf_nan_frac = s_is_nan? nan_frac : 10'h0;
	//ea-eb
	wire [4:0] exp_diff = fp_large[14:10] - fp_small[14:10];
	wire small_den_only = (fp_large[14:10] != 0) & (fp_small[14:10] == 0);
	//計算需要位移幾位,並且位移
	wire [4:0] shift_amount = small_den_only? exp_diff - 5'h1 : exp_diff;
	wire [23:0] small_frac24 = (shift_amount >= 13)? {13'h0,small_frac11} : {small_frac11,13'h0} >> shift_amount;
	//留下24bit以及保護.循環位,計算多出來的位數,使用reduction OR簡化成1bit
	assign small_frac14 = {small_frac24[23:11],|small_frac24[10:0]};
endmodule

16BIT/fp_16bit_adder.v
`include "fp_align.v"
`include "fp_reg_align_cal.v"
`include "fp_cal.v"
`include "fp_norm.v"
`include "fp_reg_cal_norm.v"
`timescale 1ns / 1ps

module pipelined_16bitfpadder (a,b,sub,rm,s,clk,clrn,e); // pipelined fp adder
	input clk, clrn; // clock and reset
	input [15:0] a, b; // fp a and b
	input [1:0] rm; // round mode
	input sub; // 1: sub; 0: add
	input e; // enable
	output [15:0] s; // fp output
	wire [13:0] a_small_frac;
	wire [10:0] a_large_frac;
	wire [9:0] a_inf_nan_frac;
	wire [4:0] a_exp;
	wire a_is_nan,a_is_inf;
	wire a_sign;
	wire a_op_sub;
	// exe1: alignment stage
	fadd_align alignment (a,b,sub,a_is_nan,a_is_inf,a_inf_nan_frac,a_sign,	a_exp,a_op_sub,a_large_frac,a_small_frac);
	wire [13:0] c_small_frac;
	wire [10:0] c_large_frac;
	wire [9:0] c_inf_nan_frac;
	wire [4:0] c_exp;
	wire [1:0] c_rm;
	wire c_is_nan,c_is_inf;
	wire c_sign;
	wire c_op_sub;
	// pipelined registers
	reg_align_cal reg_ac (rm,a_is_nan,a_is_inf,a_inf_nan_frac,a_sign,a_exp,
	a_op_sub,a_large_frac,a_small_frac,clk,clrn,e,
	c_rm,c_is_nan,c_is_inf,c_inf_nan_frac,c_sign,
	c_exp,c_op_sub,c_large_frac,c_small_frac);
	wire [14:0] c_frac;
	// exe2: calculation stage
	fadd_cal calculation (c_op_sub,c_large_frac,c_small_frac,c_frac);
	wire [14:0] n_frac;
	wire [9:0] n_inf_nan_frac;
	wire [4:0] n_exp;
	wire [1:0] n_rm;
	wire n_is_nan,n_is_inf;
	wire n_sign;
	// pipelined registers
	reg_cal_norm reg_cn (c_rm,c_is_nan,c_is_inf,c_inf_nan_frac,c_sign,c_exp,
	c_frac,clk,clrn,e,n_rm,n_is_nan,n_is_inf,
	n_inf_nan_frac,n_sign,n_exp,n_frac);
	// exe3: normalization stage
	fadd_norm normalization (n_rm,n_is_nan,n_is_inf,n_inf_nan_frac,n_sign,
	n_exp,n_frac,s);
endmodule

16BIT/16bit_adder_testbench.v
`include "fp_16bit_adder.v"//
`timescale 1ns / 1ps

module test_bench;
reg clk; //clock
reg clrn; //負緣時清空
reg[15:0] a;
reg[15:0] b;
reg en;
wire [15:0] result;
pipelined_16bitfpadder test(a,b,1'b0,2'd0,result,clk,clrn,en);


initial #0 clk = 1'b1;
always #10 clk = ~clk;
  
initial begin
	a = 16'h4500;
	b = 16'h4700;
	en = 0;
	#0 clrn = 1'b0;
	#5 clrn = 1'b0;
	#10 clrn = 1'b1;
	en = 1'b1;
	#50
	if(result==16'h4A00)
		$display("----------Correct!----------");
	else
		$display("----------Wrong!----------");
	$display("Ans:%x, yours:%x\n",16'h4A00,result);
	a = 16'h4300;
	b = 16'hC500;
	en = 0;
	#0 clrn = 1'b0;
	#5 clrn = 1'b0;
	#10 clrn = 1'b1;
	en = 1'b1;
	#50
	if(result==16'hBE00)
		$display("----------Correct!----------");
	else
		$display("----------Wrong!----------");
	$display("Ans:%x, yours:%x\n",16'hBE00,result);
	a = 16'h7BFF;
	b = 16'h7BFF;
	en = 0;
	#0 clrn = 1'b0;
	#5 clrn = 1'b0;
	#10 clrn = 1'b1;
	en = 1'b1;
	#50
	$display("----------Exp!----------");
	$display("Ans:x, yours:%x\n",result);
	#500 $finish;
end

initial begin
	$dumpfile("fpadder.vcd");
	$dumpvars;
end

endmodule

16BIT/fpadder.vcd
$date
	Sun May 20 17:58:29 2018
$end
$version
	Icarus Verilog
$end
$timescale
	1ps
$end
$scope module test_bench $end
$var wire 16 ! result [15:0] $end
$var reg 16 " a [15:0] $end
$var reg 16 # b [15:0] $end
$var reg 1 $ clk $end
$var reg 1 % clrn $end
$var reg 1 & en $end
$scope module test $end
$var wire 16 ' a [15:0] $end
$var wire 5 ( a_exp [4:0] $end
$var wire 10 ) a_inf_nan_frac [9:0] $end
$var wire 1 * a_is_inf $end
$var wire 1 + a_is_nan $end
$var wire 11 , a_large_frac [10:0] $end
$var wire 1 - a_op_sub $end
$var wire 1 . a_sign $end
$var wire 14 / a_small_frac [13:0] $end
$var wire 16 0 b [15:0] $end
$var wire 5 1 c_exp [4:0] $end
$var wire 15 2 c_frac [14:0] $end
$var wire 10 3 c_inf_nan_frac [9:0] $end
$var wire 1 4 c_is_inf $end
$var wire 1 5 c_is_nan $end
$var wire 11 6 c_large_frac [10:0] $end
$var wire 1 7 c_op_sub $end
$var wire 2 8 c_rm [1:0] $end
$var wire 1 9 c_sign $end
$var wire 14 : c_small_frac [13:0] $end
$var wire 1 ; clk $end
$var wire 1 < clrn $end
$var wire 1 = e $end
$var wire 5 > n_exp [4:0] $end
$var wire 15 ? n_frac [14:0] $end
$var wire 10 @ n_inf_nan_frac [9:0] $end
$var wire 1 A n_is_inf $end
$var wire 1 B n_is_nan $end
$var wire 2 C n_rm [1:0] $end
$var wire 1 D n_sign $end
$var wire 2 E rm [1:0] $end
$var wire 16 F s [15:0] $end
$var wire 1 G sub $end
$scope module alignment $end
$var wire 16 H a [15:0] $end
$var wire 16 I b [15:0] $end
$var wire 1 J exchange $end
$var wire 5 K exp_diff [4:0] $end
$var wire 16 L fp_large [15:0] $end
$var wire 1 M fp_large_expo_is_ff $end
$var wire 1 N fp_large_frac_is_00 $end
$var wire 1 O fp_large_hidden_bit $end
$var wire 1 P fp_large_is_inf $end
$var wire 1 Q fp_large_is_nan $end
$var wire 16 R fp_small [15:0] $end
$var wire 1 S fp_small_expo_is_ff $end
$var wire 1 T fp_small_frac_is_00 $end
$var wire 1 U fp_small_hidden_bit $end
$var wire 1 V fp_small_is_inf $end
$var wire 1 W fp_small_is_nan $end
$var wire 10 X inf_nan_frac [9:0] $end
$var wire 11 Y large_frac11 [10:0] $end
$var wire 10 Z nan_frac [9:0] $end
$var wire 1 - op_sub $end
$var wire 1 * s_is_inf $end
$var wire 1 + s_is_nan $end
$var wire 5 [ shift_amount [4:0] $end
$var wire 1 . sign $end
$var wire 1 \ small_den_only $end
$var wire 11 ] small_frac11 [10:0] $end
$var wire 14 ^ small_frac14 [13:0] $end
$var wire 24 _ small_frac24 [23:0] $end
$var wire 1 G sub $end
$var wire 5 ` temp_exp [4:0] $end
$upscope $end
$scope module reg_ac $end
$var wire 5 a a_exp [4:0] $end
$var wire 10 b a_inf_nan_frac [9:0] $end
$var wire 1 * a_is_inf $end
$var wire 1 + a_is_nan $end
$var wire 11 c a_large_frac [10:0] $end
$var wire 1 - a_op_sub $end
$var wire 2 d a_rm [1:0] $end
$var wire 1 . a_sign $end
$var wire 14 e a_small_frac [13:0] $end
$var wire 1 ; clk $end
$var wire 1 < clrn $end
$var wire 1 = e $end
$var reg 5 f c_exp [4:0] $end
$var reg 10 g c_inf_nan_frac [9:0] $end
$var reg 1 h c_is_inf $end
$var reg 1 i c_is_nan $end
$var reg 11 j c_large_frac [10:0] $end
$var reg 1 k c_op_sub $end
$var reg 2 l c_rm [1:0] $end
$var reg 1 m c_sign $end
$var reg 14 n c_small_frac [13:0] $end
$upscope $end
$scope module calculation $end
$var wire 14 o aligned_large_frac [13:0] $end
$var wire 14 p aligned_small_frac [13:0] $end
$var wire 15 q cal_frac [14:0] $end
$var wire 11 r large_frac11 [10:0] $end
$var wire 1 7 op_sub $end
$var wire 14 s small_frac14 [13:0] $end
$upscope $end
$scope module reg_cn $end
$var wire 5 t c_exp [4:0] $end
$var wire 15 u c_frac [14:0] $end
$var wire 10 v c_inf_nan_frac [9:0] $end
$var wire 1 4 c_is_inf $end
$var wire 1 5 c_is_nan $end
$var wire 2 w c_rm [1:0] $end
$var wire 1 9 c_sign $end
$var wire 1 ; clk $end
$var wire 1 < clrn $end
$var wire 1 = e $end
$var reg 5 x n_exp [4:0] $end
$var reg 15 y n_frac [14:0] $end
$var reg 10 z n_inf_nan_frac [9:0] $end
$var reg 1 { n_is_inf $end
$var reg 1 | n_is_nan $end
$var reg 2 } n_rm [1:0] $end
$var reg 1 ~ n_sign $end
$upscope $end
$scope module normalization $end
$var wire 15 !" cal_frac [14:0] $end
$var wire 5 "" exponent [4:0] $end
$var wire 16 #" f0 [15:0] $end
$var wire 16 $" f1 [15:0] $end
$var wire 16 %" f2 [15:0] $end
$var wire 16 &" f3 [15:0] $end
$var wire 1 '" frac_plus_1 $end
$var wire 12 (" frac_round [11:0] $end
$var wire 10 )" inf_nan_frac [9:0] $end
$var wire 1 A is_inf $end
$var wire 1 B is_nan $end
$var wire 1 *" overflow $end
$var wire 2 +" rm [1:0] $end
$var wire 16 ," s [15:0] $end
$var wire 1 D sign $end
$var wire 5 -" temp_exp [4:0] $end
$var wire 4 ." zeros [3:0] $end
$var reg 5 /" exp0 [4:0] $end
$var reg 14 0" frac0 [13:0] $end
$scope function final_result $end
$var reg 5 1" exponent [4:0] $end
$var reg 16 2" final_result [15:0] $end
$var reg 10 3" fraction [9:0] $end
$var reg 10 4" inf_nan_frac [9:0] $end
$var reg 1 5" is_inf $end
$var reg 1 6" is_nan $end
$var reg 1 7" overflow $end
$var reg 2 8" rm [1:0] $end
$var reg 1 9" sign $end
$upscope $end
$upscope $end
$upscope $end
$upscope $end
$enddefinitions $end
#0
$dumpvars
09"
b0 8"
07"
06"
05"
b0 4"
b0 3"
b0 2"
b0 1"
b0 0"
b0 /"
b1111 ."
b0 -"
b0 ,"
b0 +"
0*"
b0 )"
b0 ("
0'"
b0 &"
b0 %"
b0 $"
b0 #"
b0 ""
b0 !"
0~
b0 }
0|
0{
b0 z
b0 y
b0 x
b0 w
b0 v
b0 u
b0 t
b0 s
b0 r
b0 q
b0 p
b0 o
b0 n
0m
b0 l
0k
b0 j
0i
0h
b0 g
b0 f
b10100000000000 e
b0 d
b11100000000 c
b0 b
b10001 a
b10001 `
b101000000000000000000000 _
b10100000000000 ^
b10100000000 ]
0\
b0 [
b1100000000 Z
b11100000000 Y
b0 X
0W
0V
1U
0T
0S
b100010100000000 R
0Q
0P
1O
0N
0M
b100011100000000 L
b0 K
1J
b100011100000000 I
b100010100000000 H
0G
b0 F
b0 E
0D
b0 C
0B
0A
b0 @
b0 ?
b0 >
0=
0<
1;
b0 :
09
b0 8
07
b0 6
05
04
b0 3
b0 2
b0 1
b100011100000000 0
b10100000000000 /
0.
0-
b11100000000 ,
0+
0*
b0 )
b10001 (
b100010100000000 '
0&
0%
1$
b100011100000000 #
b100010100000000 "
b0 !
$end
#10000
0$
0;
#15000
1&
1=
1%
1<
#20000
b110000000000000 2
b110000000000000 q
b110000000000000 u
b10100000000000 p
b11100000000000 o
b10100000000000 n
b10100000000000 :
b10100000000000 s
b11100000000 j
b11100000000 6
b11100000000 r
b10001 f
b10001 1
b10001 t
1$
1;
#30000
0$
0;
#40000
b10000000000000 #"
b10000000000000 $"
b10000000000000 %"
b10000000000000 &"
b100101000000000 !
b100101000000000 F
b100101000000000 ,"
b100101000000000 2"
b1000000000 3"
b10010 1"
b10010 ""
b11000000000 ("
b0 ."
b10010 /"
b11000000000000 0"
b110000000000000 y
b110000000000000 ?
b110000000000000 !"
b10001 x
b10001 >
b10001 -"
1$
1;
#50000
0$
0;
#60000
1$
1;
#65000
b0 #"
b0 $"
b0 3"
b0 %"
b0 !
b0 F
b0 ,"
b0 2"
b0 1"
b0 2
b0 q
b0 u
b0 &"
b0 ("
b0 ""
b0 p
b0 o
b1111 ."
b0 0"
b0 /"
b0 n
b0 :
b0 s
b0 j
b0 6
b0 r
b0 f
b0 1
b0 t
b0 y
b0 ?
b0 !"
b0 x
b0 >
b0 -"
1-
b1110000000000 /
b1110000000000 ^
b1110000000000 e
1.
b11100000000000000000000 _
b1 [
b10100000000 ,
b10100000000 Y
b10100000000 c
b11100000000 ]
b1 K
0%
0<
b1100010100000000 L
b100001100000000 R
0&
0=
b1100010100000000 #
b1100010100000000 0
b1100010100000000 I
b100001100000000 "
b100001100000000 '
b100001100000000 H
#70000
0$
0;
#80000
b110000000000 2
b110000000000 q
b110000000000 u
b1110000000000 p
b10100000000000 o
b1110000000000 n
b1110000000000 :
b1110000000000 s
b10100000000 j
b10100000000 6
b10100000000 r
1k
17
b10001 f
b10001 1
b10001 t
1m
19
1&
1=
1%
1<
1$
1;
#90000
0$
0;
#100000
b1000000000 3"
b1111 1"
b11000000000 ("
b1111 ""
b11000000000000 0"
b1111 /"
b11000000000000 #"
b11000000000000 $"
b110000000000 %"
b110000000000 &"
b10 ."
b1011111000000000 !
b1011111000000000 F
b1011111000000000 ,"
b1011111000000000 2"
19"
b110000000000 y
b110000000000 ?
b110000000000 !"
b10001 x
b10001 >
b10001 -"
1~
1D
1$
1;
#110000
0$
0;
#120000
1$
1;
#130000
b0 #"
b0 $"
b0 3"
b0 %"
b0 1"
b0 &"
b0 ("
b0 ""
b0 p
b0 o
b0 2
b0 q
b0 u
b1111 ."
b0 0"
b0 /"
b0 !
b0 F
b0 ,"
b0 2"
09"
b0 n
b0 :
b0 s
b0 j
b0 6
b0 r
0k
07
b0 f
b0 1
b0 t
0m
09
b0 y
b0 ?
b0 !"
b0 x
b0 >
b0 -"
0~
0D
0-
b11111111111000 /
b11111111111000 ^
b11111111111000 e
b111111111110000000000000 _
b0 [
b11111111111 ,
b11111111111 Y
b11111111111 c
b11110 (
b11110 `
b11110 a
0.
b11111111111 ]
b0 K
b1111111111 Z
0%
0<
b111101111111111 L
0J
b111101111111111 R
0$
0;
0&
0=
b111101111111111 #
b111101111111111 0
b111101111111111 I
b111101111111111 "
b111101111111111 '
b111101111111111 H
#140000
1$
1;
#145000
1&
1=
1%
1<
#150000
0$
0;
#160000
b111111111110000 2
b111111111110000 q
b111111111110000 u
b11111111111000 p
b11111111111000 o
b11111111111000 n
b11111111111000 :
b11111111111000 s
b11111111111 j
b11111111111 6
b11111111111 r
b11110 f
b11110 1
b11110 t
1$
1;
#170000
0$
0;
#180000
b11111111110000 #"
b11111111110000 $"
b11111111110000 %"
b111110000000000 !
b111110000000000 F
b111110000000000 ,"
b111110000000000 2"
b1111111111 3"
b11111 1"
17"
b11111111110000 &"
b11111 ""
1*"
b11111111111 ("
b0 ."
b11111 /"
b11111111111000 0"
b111111111110000 y
b111111111110000 ?
b111111111110000 !"
b11110 x
b11110 >
b11110 -"
1$
1;
